image_processor_raphaelhfs/__init__.py
image_processor_raphaelhfs/process/__init__.py
image_processor_raphaelhfs/process/combine.py
image_processor_raphaelhfs/process/transform.py
image_processor_raphaelhfs/py.typed
image_processor_raphaelhfs/utils/__init__.py
image_processor_raphaelhfs/utils/io.py
image_processor_raphaelhfs/utils/plot.py
image_processor_raphaelhfs-0.1.0.dist-info/WHEEL
image_processor_raphaelhfs-0.1.0.dist-info/METADATA
image_processor_raphaelhfs-0.1.0.dist-info/RECORD
