Metadata-Version: 2.3
Name: image-processor-raphaelhfs
Version: 0.1.0
Summary: A simple yet modern package for image processing.
Author: Raphael H. F. Silva
Author-email: Raphael H. F. Silva <147460456+raphael-hfs@users.noreply.github.com>
Requires-Dist: matplotlib>=3.10.8
Requires-Dist: numpy>=2.4.1
Requires-Dist: scikit-image>=0.26.0
Requires-Python: >=3.14
